mcp_server_calculator/__init__.py
mcp_server_calculator/__main__.py
mcp_server_calculator/calculator.py
mseep_mcp_server_calculator-0.2.7.dist-info/licenses/LICENSE
mseep_mcp_server_calculator-0.2.7.dist-info/METADATA
mseep_mcp_server_calculator-0.2.7.dist-info/WHEEL
mseep_mcp_server_calculator-0.2.7.dist-info/entry_points.txt
mseep_mcp_server_calculator-0.2.7.dist-info/top_level.txt
mseep_mcp_server_calculator-0.2.7.dist-info/RECORD
